{
    "fluentMethods": true,
    "relationships": [],
    "fields": [
        {
            "fieldName": "name",
            "fieldType": "String",
            "fieldValidateRules": [
                "required"
            ]
        },
        {
            "fieldName": "description",
            "fieldType": "String"
        },
        {
            "fieldName": "createdBy",
            "fieldType": "String"
        },
        {
            "fieldName": "createdAt",
            "fieldType": "Instant"
        },
        {
            "fieldName": "updatedBy",
            "fieldType": "String"
        },
        {
            "fieldName": "updatedAt",
            "fieldType": "Instant"
        }
    ],
    "changelogDate": "20180329103116",
    "entityTableName": "ab_travel_purposes",
    "dto": "mapstruct",
    "pagination": "no",
    "service": "no",
    "jpaMetamodelFiltering": false,
    "microserviceName": "hcmAbsMicroservice"
}